med_blosc2/__init__.py
med_blosc2/med_blosc2.py
med_blosc2/meta.py
med_blosc2/utils.py
med_blosc2-0.0.5.dist-info/licenses/LICENSE
med_blosc2-0.0.5.dist-info/METADATA
med_blosc2-0.0.5.dist-info/WHEEL
med_blosc2-0.0.5.dist-info/top_level.txt
med_blosc2-0.0.5.dist-info/RECORD
