Metadata-Version: 2.4
Name: med-blosc2
Version: 0.0.5
Summary: A standardized blosc2 image reader and writer for medical images.
Author-email: Karol Gotkowski <karol.gotkowski@dkfz.de>
License: MIT
Project-URL: Homepage, https://github.com/Karol-G/med-blosc2
Project-URL: Source, https://github.com/Karol-G/med-blosc2
Project-URL: Issues, https://github.com/Karol-G/med-blosc2/issues
Keywords: copier,template,python
Classifier: Programming Language :: Python :: 3
Classifier: Programming Language :: Python :: 3.10
Classifier: Programming Language :: Python :: 3.11
Classifier: Programming Language :: Python :: 3.12
Classifier: Operating System :: OS Independent
Requires-Python: >=3.10
License-File: LICENSE
Requires-Dist: blosc2>=3
Requires-Dist: numpy>=2
Provides-Extra: dev
Requires-Dist: build>=1.0; extra == "dev"
Requires-Dist: pytest>=7.0; extra == "dev"
Requires-Dist: twine>=4.0; extra == "dev"
Requires-Dist: setuptools_scm[toml]>=8.0; extra == "dev"
Dynamic: license-file
